{
    "82": {
        "impLoc": 89,
        "impFac": 1.8023678958179208
    },
    "95": {
        "freezeLoc": 188,
        "freezeDur": 137
    },
    "113": {
        "noiseLoc": 192,
        "noiseDur": 63
    },
    "126": {
        "impLoc": 188,
        "impFac": 1.5195521951338935
    },
    "145": {
        "driftLoc": 35,
        "driftDur": 198,
        "driftFact": 477.6539942419794
    },
    "232": {
        "freezeLoc": 153,
        "freezeDur": 74
    },
    "243": {
        "impLoc": 231,
        "impFac": 1.9870049055734318
    },
    "248": {
        "driftLoc": 45,
        "driftDur": 183,
        "driftFact": 419.111879530589
    },
    "249": {
        "freezeLoc": 38,
        "freezeDur": 146
    },
    "307": {
        "offsetLoc": 98,
        "offsetDur": 41
    },
    "320": {
        "noiseLoc": 155,
        "noiseDur": 96
    },
    "378": {
        "offsetLoc": 113,
        "offsetDur": 84
    },
    "383": {
        "impLoc": 258,
        "impFac": 1.6320593794567713
    },
    "386": {
        "freezeLoc": 9,
        "freezeDur": 83
    },
    "395": {
        "driftLoc": 79,
        "driftDur": 200,
        "driftFact": 249.39857023716328
    },
    "411": {
        "offsetLoc": 34,
        "offsetDur": 113
    },
    "414": {
        "noiseLoc": 99,
        "noiseDur": 98
    },
    "418": {
        "driftLoc": 84,
        "driftDur": 213,
        "driftFact": 476.79048973912177
    },
    "463": {
        "offsetLoc": 47,
        "offsetDur": 78
    },
    "474": {
        "driftLoc": 18,
        "driftDur": 233,
        "driftFact": 171.92636314651946
    },
    "475": {
        "offsetLoc": 194,
        "offsetDur": 72
    },
    "480": {
        "impLoc": 197,
        "impFac": 1.5508856934041264
    },
    "486": {
        "driftLoc": 93,
        "driftDur": 175,
        "driftFact": 157.04697447747935
    },
    "521": {
        "offsetLoc": 35,
        "offsetDur": 140
    },
    "529": {
        "offsetLoc": 199,
        "offsetDur": 115
    },
    "534": {
        "noiseLoc": 72,
        "noiseDur": 84
    },
    "548": {
        "noiseLoc": 25,
        "noiseDur": 99
    },
    "567": {
        "noiseLoc": 92,
        "noiseDur": 115
    },
    "581": {
        "noiseLoc": 51,
        "noiseDur": 42
    },
    "592": {
        "driftLoc": 52,
        "driftDur": 168,
        "driftFact": 275.54111052535166
    },
    "604": {
        "noiseLoc": 33,
        "noiseDur": 101
    },
    "635": {
        "offsetLoc": 131,
        "offsetDur": 154
    },
    "643": {
        "noiseLoc": 89,
        "noiseDur": 104
    },
    "708": {
        "freezeLoc": 124,
        "freezeDur": 116
    },
    "727": {
        "freezeLoc": 138,
        "freezeDur": 78
    },
    "732": {
        "driftLoc": 17,
        "driftDur": 179,
        "driftFact": 289.3055686971038
    },
    "739": {
        "impLoc": 142,
        "impFac": 1.9378494013262642
    },
    "758": {
        "offsetLoc": 42,
        "offsetDur": 100
    },
    "767": {
        "noiseLoc": 38,
        "noiseDur": 98
    },
    "768": {
        "freezeLoc": 61,
        "freezeDur": 58
    },
    "812": {
        "impLoc": 105,
        "impFac": 1.6329836373985758
    },
    "818": {
        "offsetLoc": 97,
        "offsetDur": 135
    },
    "863": {
        "driftLoc": 25,
        "driftDur": 182,
        "driftFact": 134.78614104535166
    },
    "877": {
        "freezeLoc": 37,
        "freezeDur": 83
    },
    "884": {
        "freezeLoc": 7,
        "freezeDur": 121
    },
    "917": {
        "noiseLoc": 100,
        "noiseDur": 143
    },
    "927": {
        "driftLoc": 85,
        "driftDur": 184,
        "driftFact": 279.4981320956603
    },
    "931": {
        "offsetLoc": 16,
        "offsetDur": 158
    },
    "982": {
        "driftLoc": 5,
        "driftDur": 178,
        "driftFact": 453.54434825389444
    },
    "1033": {
        "noiseLoc": 98,
        "noiseDur": 80
    },
    "1105": {
        "offsetLoc": 147,
        "offsetDur": 70
    },
    "1133": {
        "noiseLoc": 80,
        "noiseDur": 67
    },
    "1146": {
        "impLoc": 213,
        "impFac": 1.464546864331378
    },
    "1148": {
        "impLoc": 232,
        "impFac": 1.9124971813057536
    },
    "1152": {
        "driftLoc": 45,
        "driftDur": 219,
        "driftFact": 297.2745576549771
    },
    "1164": {
        "noiseLoc": 24,
        "noiseDur": 77
    },
    "1165": {
        "offsetLoc": 95,
        "offsetDur": 102
    },
    "1207": {
        "noiseLoc": 105,
        "noiseDur": 119
    },
    "1216": {
        "noiseLoc": 197,
        "noiseDur": 55
    },
    "1231": {
        "driftLoc": 36,
        "driftDur": 250,
        "driftFact": 141.90338955583584
    },
    "1234": {
        "offsetLoc": 26,
        "offsetDur": 158
    },
    "1235": {
        "impLoc": 323,
        "impFac": 1.7888075984111533
    },
    "1265": {
        "impLoc": 82,
        "impFac": 1.6043256783123812
    },
    "1269": {
        "driftLoc": 58,
        "driftDur": 175,
        "driftFact": 321.39539955667914
    },
    "1339": {
        "impLoc": 203,
        "impFac": 1.5498717901570611
    },
    "1356": {
        "driftLoc": 21,
        "driftDur": 201,
        "driftFact": 467.8854349903534
    },
    "1367": {
        "impLoc": 42,
        "impFac": 1.5580058761344575
    },
    "1373": {
        "noiseLoc": 114,
        "noiseDur": 75
    },
    "1419": {
        "driftLoc": 49,
        "driftDur": 217,
        "driftFact": 486.84686060294786
    },
    "1422": {
        "offsetLoc": 11,
        "offsetDur": 52
    },
    "1427": {
        "freezeLoc": 21,
        "freezeDur": 75
    },
    "1447": {
        "noiseLoc": 97,
        "noiseDur": 52
    },
    "1499": {
        "driftLoc": 69,
        "driftDur": 202,
        "driftFact": 104.53563702249782
    },
    "1514": {
        "noiseLoc": 108,
        "noiseDur": 121
    },
    "1517": {
        "impLoc": 266,
        "impFac": 1.5807526088948796
    },
    "1520": {
        "impLoc": 304,
        "impFac": 1.8552650993553286
    },
    "1521": {
        "driftLoc": 13,
        "driftDur": 216,
        "driftFact": 271.5914040473741
    },
    "1553": {
        "impLoc": 319,
        "impFac": 1.519506123122399
    },
    "1655": {
        "offsetLoc": 29,
        "offsetDur": 102
    },
    "1673": {
        "noiseLoc": 127,
        "noiseDur": 81
    },
    "1741": {
        "impLoc": 245,
        "impFac": 1.4276679337002764
    },
    "1744": {
        "impLoc": 203,
        "impFac": 1.957672301432594
    },
    "1746": {
        "offsetLoc": 181,
        "offsetDur": 49
    },
    "1790": {
        "impLoc": 316,
        "impFac": 1.6096080667339114
    },
    "1822": {
        "freezeLoc": 13,
        "freezeDur": 130
    },
    "1825": {
        "freezeLoc": 67,
        "freezeDur": 53
    },
    "1826": {
        "freezeLoc": 61,
        "freezeDur": 149
    },
    "1854": {
        "offsetLoc": 157,
        "offsetDur": 99
    },
    "1855": {
        "freezeLoc": 192,
        "freezeDur": 145
    },
    "1873": {
        "impLoc": 184,
        "impFac": 1.9406353218956731
    },
    "1884": {
        "freezeLoc": 167,
        "freezeDur": 59
    },
    "1889": {
        "freezeLoc": 72,
        "freezeDur": 86
    },
    "1911": {
        "impLoc": 336,
        "impFac": 1.5652168967691389
    },
    "1912": {
        "offsetLoc": 171,
        "offsetDur": 44
    },
    "1913": {
        "offsetLoc": 199,
        "offsetDur": 67
    },
    "1924": {
        "noiseLoc": 111,
        "noiseDur": 53
    },
    "1980": {
        "freezeLoc": 186,
        "freezeDur": 54
    },
    "2025": {
        "noiseLoc": 12,
        "noiseDur": 61
    },
    "2047": {
        "freezeLoc": 5,
        "freezeDur": 155
    },
    "2055": {
        "impLoc": 135,
        "impFac": 1.9855883178325762
    },
    "2066": {
        "driftLoc": 52,
        "driftDur": 241,
        "driftFact": 443.2092729921927
    },
    "2102": {
        "noiseLoc": 55,
        "noiseDur": 46
    },
    "2208": {
        "freezeLoc": 54,
        "freezeDur": 56
    },
    "2211": {
        "freezeLoc": 183,
        "freezeDur": 54
    },
    "2226": {
        "driftLoc": 43,
        "driftDur": 248,
        "driftFact": 373.5712161055654
    },
    "2234": {
        "freezeLoc": 120,
        "freezeDur": 131
    },
    "2238": {
        "offsetLoc": 20,
        "offsetDur": 129
    },
    "2257": {
        "noiseLoc": 43,
        "noiseDur": 133
    },
    "2283": {
        "offsetLoc": 183,
        "offsetDur": 70
    },
    "2285": {
        "impLoc": 207,
        "impFac": 1.9640166749390673
    },
    "2290": {
        "driftLoc": 53,
        "driftDur": 247,
        "driftFact": 422.00183058533935
    },
    "2295": {
        "impLoc": 122,
        "impFac": 1.8108678107360139
    },
    "2321": {
        "noiseLoc": 124,
        "noiseDur": 80
    },
    "2323": {
        "driftLoc": 93,
        "driftDur": 232,
        "driftFact": 235.037847018355
    },
    "2375": {
        "freezeLoc": 136,
        "freezeDur": 149
    },
    "2376": {
        "noiseLoc": 187,
        "noiseDur": 111
    },
    "2386": {
        "freezeLoc": 96,
        "freezeDur": 114
    },
    "2391": {
        "freezeLoc": 152,
        "freezeDur": 39
    },
    "2450": {
        "freezeLoc": 53,
        "freezeDur": 86
    },
    "2468": {
        "offsetLoc": 167,
        "offsetDur": 72
    },
    "2490": {
        "offsetLoc": 126,
        "offsetDur": 34
    },
    "2517": {
        "offsetLoc": 142,
        "offsetDur": 112
    },
    "2522": {
        "offsetLoc": 46,
        "offsetDur": 146
    },
    "2527": {
        "offsetLoc": 117,
        "offsetDur": 135
    },
    "2546": {
        "noiseLoc": 75,
        "noiseDur": 51
    },
    "2559": {
        "freezeLoc": 131,
        "freezeDur": 134
    },
    "2571": {
        "freezeLoc": 162,
        "freezeDur": 55
    },
    "2575": {
        "offsetLoc": 101,
        "offsetDur": 72
    },
    "2582": {
        "noiseLoc": 18,
        "noiseDur": 54
    },
    "2583": {
        "noiseLoc": 184,
        "noiseDur": 119
    },
    "2600": {
        "freezeLoc": 30,
        "freezeDur": 131
    },
    "2635": {
        "freezeLoc": 29,
        "freezeDur": 91
    },
    "2646": {
        "driftLoc": 88,
        "driftDur": 156,
        "driftFact": 210.5739546766789
    },
    "2672": {
        "driftLoc": 27,
        "driftDur": 238,
        "driftFact": 278.5323103912174
    },
    "2691": {
        "impLoc": 310,
        "impFac": 1.4069482588202618
    },
    "2713": {
        "freezeLoc": 20,
        "freezeDur": 150
    },
    "2756": {
        "driftLoc": 94,
        "driftDur": 182,
        "driftFact": 408.00822296917363
    },
    "2790": {
        "noiseLoc": 10,
        "noiseDur": 38
    },
    "2805": {
        "freezeLoc": 171,
        "freezeDur": 62
    },
    "2811": {
        "freezeLoc": 99,
        "freezeDur": 155
    },
    "2817": {
        "impLoc": 247,
        "impFac": 1.853319499317752
    },
    "2824": {
        "impLoc": 318,
        "impFac": 1.796985848702628
    },
    "2857": {
        "driftLoc": 96,
        "driftDur": 204,
        "driftFact": 277.04115691317975
    },
    "2862": {
        "impLoc": 100,
        "impFac": 1.5128632986644746
    },
    "2892": {
        "impLoc": 76,
        "impFac": 1.5355618652767267
    },
    "2910": {
        "noiseLoc": 187,
        "noiseDur": 141
    },
    "2944": {
        "freezeLoc": 178,
        "freezeDur": 114
    },
    "2964": {
        "impLoc": 284,
        "impFac": 1.9399684492027842
    },
    "2975": {
        "driftLoc": 40,
        "driftDur": 238,
        "driftFact": 197.60461612840248
    },
    "2985": {
        "driftLoc": 97,
        "driftDur": 243,
        "driftFact": 367.7448278176397
    },
    "3022": {
        "driftLoc": 1,
        "driftDur": 156,
        "driftFact": 430.0616276347336
    },
    "3064": {
        "impLoc": 103,
        "impFac": 1.9843800596552226
    },
    "3075": {
        "freezeLoc": 136,
        "freezeDur": 38
    },
    "3082": {
        "offsetLoc": 135,
        "offsetDur": 139
    },
    "3088": {
        "noiseLoc": 76,
        "noiseDur": 71
    },
    "3121": {
        "noiseLoc": 141,
        "noiseDur": 136
    },
    "3125": {
        "offsetLoc": 122,
        "offsetDur": 148
    },
    "3146": {
        "freezeLoc": 157,
        "freezeDur": 102
    },
    "3147": {
        "freezeLoc": 160,
        "freezeDur": 66
    },
    "3168": {
        "freezeLoc": 51,
        "freezeDur": 35
    },
    "3191": {
        "offsetLoc": 61,
        "offsetDur": 154
    },
    "3201": {
        "offsetLoc": 190,
        "offsetDur": 84
    },
    "3209": {
        "offsetLoc": 61,
        "offsetDur": 36
    },
    "3246": {
        "offsetLoc": 31,
        "offsetDur": 133
    },
    "3271": {
        "impLoc": 17,
        "impFac": 1.5775212417008078
    },
    "3319": {
        "impLoc": 338,
        "impFac": 1.5434594920293057
    },
    "3331": {
        "offsetLoc": 155,
        "offsetDur": 78
    },
    "3353": {
        "noiseLoc": 80,
        "noiseDur": 72
    },
    "3398": {
        "impLoc": 68,
        "impFac": 1.5329704463029497
    },
    "3418": {
        "noiseLoc": 41,
        "noiseDur": 112
    },
    "3432": {
        "offsetLoc": 102,
        "offsetDur": 37
    },
    "3486": {
        "offsetLoc": 65,
        "offsetDur": 101
    },
    "3495": {
        "noiseLoc": 170,
        "noiseDur": 51
    },
    "3497": {
        "noiseLoc": 158,
        "noiseDur": 74
    },
    "3506": {
        "impLoc": 198,
        "impFac": 1.8443374132165526
    },
    "3547": {
        "impLoc": 259,
        "impFac": 1.8348213804663012
    },
    "3557": {
        "offsetLoc": 66,
        "offsetDur": 159
    },
    "3579": {
        "noiseLoc": 19,
        "noiseDur": 75
    },
    "3640": {
        "impLoc": 134,
        "impFac": 1.827335732761607
    },
    "3672": {
        "impLoc": 113,
        "impFac": 1.963873057387263
    },
    "3709": {
        "impLoc": 162,
        "impFac": 1.9142205889239698
    },
    "3720": {
        "impLoc": 22,
        "impFac": 1.96958115403541
    },
    "3730": {
        "noiseLoc": 134,
        "noiseDur": 112
    },
    "3745": {
        "noiseLoc": 168,
        "noiseDur": 98
    },
    "3781": {
        "impLoc": 307,
        "impFac": 1.78084016904859
    },
    "3846": {
        "offsetLoc": 87,
        "offsetDur": 43
    },
    "3859": {
        "noiseLoc": 193,
        "noiseDur": 101
    },
    "3874": {
        "freezeLoc": 189,
        "freezeDur": 59
    },
    "3888": {
        "freezeLoc": 183,
        "freezeDur": 152
    },
    "3893": {
        "freezeLoc": 132,
        "freezeDur": 52
    },
    "3909": {
        "offsetLoc": 160,
        "offsetDur": 105
    },
    "3915": {
        "noiseLoc": 87,
        "noiseDur": 61
    },
    "3968": {
        "driftLoc": 29,
        "driftDur": 252,
        "driftFact": 135.04593205057796
    },
    "4059": {
        "offsetLoc": 99,
        "offsetDur": 142
    },
    "4083": {
        "freezeLoc": 170,
        "freezeDur": 134
    },
    "4140": {
        "driftLoc": 7,
        "driftDur": 245,
        "driftFact": 336.28167036749215
    },
    "4142": {
        "impLoc": 137,
        "impFac": 1.7540094229158543
    },
    "4155": {
        "freezeLoc": 63,
        "freezeDur": 92
    },
    "4182": {
        "freezeLoc": 6,
        "freezeDur": 142
    },
    "4185": {
        "offsetLoc": 147,
        "offsetDur": 138
    },
    "4202": {
        "freezeLoc": 32,
        "freezeDur": 70
    },
    "4210": {
        "noiseLoc": 116,
        "noiseDur": 108
    },
    "4310": {
        "driftLoc": 10,
        "driftDur": 171,
        "driftFact": 448.4360545406057
    },
    "4315": {
        "driftLoc": 18,
        "driftDur": 182,
        "driftFact": 223.07868999563226
    },
    "4363": {
        "driftLoc": 22,
        "driftDur": 219,
        "driftFact": 229.2323955756453
    },
    "4467": {
        "freezeLoc": 9,
        "freezeDur": 71
    },
    "4474": {
        "offsetLoc": 75,
        "offsetDur": 126
    },
    "4493": {
        "impLoc": 254,
        "impFac": 1.5901677590503278
    },
    "4532": {
        "offsetLoc": 198,
        "offsetDur": 60
    },
    "4571": {
        "impLoc": 285,
        "impFac": 1.8686304310540742
    },
    "4577": {
        "impLoc": 154,
        "impFac": 1.6740749925768856
    },
    "4581": {
        "impLoc": 243,
        "impFac": 1.4666912749320615
    },
    "4584": {
        "noiseLoc": 42,
        "noiseDur": 100
    },
    "4606": {
        "offsetLoc": 137,
        "offsetDur": 110
    },
    "4632": {
        "noiseLoc": 54,
        "noiseDur": 109
    },
    "4639": {
        "impLoc": 109,
        "impFac": 1.478290868420398
    },
    "4650": {
        "offsetLoc": 103,
        "offsetDur": 103
    },
    "4669": {
        "freezeLoc": 70,
        "freezeDur": 137
    },
    "4703": {
        "noiseLoc": 73,
        "noiseDur": 102
    },
    "4729": {
        "offsetLoc": 91,
        "offsetDur": 121
    },
    "4754": {
        "noiseLoc": 153,
        "noiseDur": 63
    },
    "4857": {
        "impLoc": 250,
        "impFac": 1.9431612221185572
    },
    "4888": {
        "impLoc": 238,
        "impFac": 1.4032857310831879
    },
    "4900": {
        "driftLoc": 90,
        "driftDur": 161,
        "driftFact": 314.91059311388653
    },
    "4943": {
        "offsetLoc": 37,
        "offsetDur": 109
    },
    "4944": {
        "impLoc": 330,
        "impFac": 1.8410756871115488
    },
    "4954": {
        "driftLoc": 5,
        "driftDur": 246,
        "driftFact": 331.2869825585565
    },
    "4961": {
        "driftLoc": 54,
        "driftDur": 167,
        "driftFact": 497.5395316431085
    },
    "4993": {
        "driftLoc": 63,
        "driftDur": 199,
        "driftFact": 272.13921805870586
    },
    "5015": {
        "noiseLoc": 12,
        "noiseDur": 84
    },
    "5024": {
        "noiseLoc": 91,
        "noiseDur": 106
    },
    "5030": {
        "offsetLoc": 59,
        "offsetDur": 45
    },
    "5058": {
        "offsetLoc": 90,
        "offsetDur": 101
    },
    "5103": {
        "noiseLoc": 27,
        "noiseDur": 142
    },
    "5120": {
        "driftLoc": 0,
        "driftDur": 233,
        "driftFact": 126.87823351191096
    },
    "5130": {
        "impLoc": 144,
        "impFac": 1.763882077334526
    },
    "5161": {
        "freezeLoc": 135,
        "freezeDur": 76
    },
    "5219": {
        "impLoc": 292,
        "impFac": 1.9154645683131917
    },
    "5223": {
        "freezeLoc": 108,
        "freezeDur": 35
    },
    "5226": {
        "driftLoc": 68,
        "driftDur": 238,
        "driftFact": 192.56964472477299
    },
    "5239": {
        "noiseLoc": 83,
        "noiseDur": 47
    },
    "5261": {
        "offsetLoc": 187,
        "offsetDur": 105
    },
    "5280": {
        "impLoc": 319,
        "impFac": 1.5766157148309619
    },
    "5325": {
        "freezeLoc": 171,
        "freezeDur": 91
    },
    "5326": {
        "freezeLoc": 123,
        "freezeDur": 101
    },
    "5338": {
        "noiseLoc": 168,
        "noiseDur": 79
    },
    "5349": {
        "noiseLoc": 157,
        "noiseDur": 110
    },
    "5376": {
        "offsetLoc": 120,
        "offsetDur": 100
    },
    "5382": {
        "freezeLoc": 174,
        "freezeDur": 122
    },
    "5423": {
        "noiseLoc": 138,
        "noiseDur": 84
    },
    "5440": {
        "driftLoc": 69,
        "driftDur": 194,
        "driftFact": 404.2998580790065
    },
    "5442": {
        "freezeLoc": 39,
        "freezeDur": 102
    },
    "5465": {
        "driftLoc": 29,
        "driftDur": 230,
        "driftFact": 278.08976850513835
    },
    "5469": {
        "freezeLoc": 158,
        "freezeDur": 118
    },
    "5481": {
        "freezeLoc": 182,
        "freezeDur": 145
    },
    "5485": {
        "impLoc": 288,
        "impFac": 1.4186455012491943
    },
    "5489": {
        "impLoc": 179,
        "impFac": 1.5428525607355592
    },
    "5490": {
        "freezeLoc": 168,
        "freezeDur": 155
    },
    "5495": {
        "driftLoc": 41,
        "driftDur": 180,
        "driftFact": 480.3124995319572
    },
    "5501": {
        "offsetLoc": 35,
        "offsetDur": 37
    },
    "5522": {
        "noiseLoc": 129,
        "noiseDur": 36
    },
    "5524": {
        "noiseLoc": 85,
        "noiseDur": 36
    },
    "5585": {
        "offsetLoc": 15,
        "offsetDur": 118
    },
    "5609": {
        "impLoc": 176,
        "impFac": 1.7559022289211146
    },
    "5654": {
        "impLoc": 33,
        "impFac": 1.6626945493458234
    },
    "5661": {
        "noiseLoc": 98,
        "noiseDur": 74
    },
    "5663": {
        "impLoc": 21,
        "impFac": 1.973750638061944
    },
    "5682": {
        "noiseLoc": 198,
        "noiseDur": 99
    },
    "5685": {
        "driftLoc": 57,
        "driftDur": 203,
        "driftFact": 294.8146710652635
    },
    "5744": {
        "noiseLoc": 112,
        "noiseDur": 113
    },
    "5746": {
        "offsetLoc": 123,
        "offsetDur": 109
    },
    "5749": {
        "driftLoc": 61,
        "driftDur": 243,
        "driftFact": 277.82016327620886
    },
    "5764": {
        "driftLoc": 34,
        "driftDur": 220,
        "driftFact": 488.7436118305649
    },
    "5782": {
        "freezeLoc": 178,
        "freezeDur": 155
    },
    "5819": {
        "impLoc": 78,
        "impFac": 1.890872412552065
    },
    "5844": {
        "freezeLoc": 151,
        "freezeDur": 139
    },
    "5853": {
        "offsetLoc": 135,
        "offsetDur": 31
    },
    "5877": {
        "offsetLoc": 147,
        "offsetDur": 70
    },
    "5914": {
        "offsetLoc": 113,
        "offsetDur": 157
    },
    "5923": {
        "driftLoc": 99,
        "driftDur": 212,
        "driftFact": 455.24413118278846
    },
    "5929": {
        "impLoc": 51,
        "impFac": 1.9226782316842346
    },
    "5977": {
        "freezeLoc": 26,
        "freezeDur": 118
    },
    "5988": {
        "freezeLoc": 148,
        "freezeDur": 97
    },
    "5995": {
        "noiseLoc": 191,
        "noiseDur": 137
    },
    "6001": {
        "noiseLoc": 43,
        "noiseDur": 78
    },
    "6008": {
        "freezeLoc": 193,
        "freezeDur": 79
    },
    "6014": {
        "impLoc": 191,
        "impFac": 1.4073620865155698
    },
    "6023": {
        "freezeLoc": 106,
        "freezeDur": 79
    },
    "6071": {
        "driftLoc": 26,
        "driftDur": 225,
        "driftFact": 219.92150816729873
    },
    "6204": {
        "freezeLoc": 94,
        "freezeDur": 112
    },
    "6224": {
        "freezeLoc": 118,
        "freezeDur": 70
    },
    "6250": {
        "freezeLoc": 175,
        "freezeDur": 78
    },
    "6261": {
        "impLoc": 249,
        "impFac": 1.9882640432211112
    },
    "6262": {
        "driftLoc": 36,
        "driftDur": 166,
        "driftFact": 396.7820809969255
    },
    "6275": {
        "offsetLoc": 133,
        "offsetDur": 100
    },
    "6276": {
        "offsetLoc": 64,
        "offsetDur": 139
    },
    "6371": {
        "driftLoc": 73,
        "driftDur": 237,
        "driftFact": 185.93561338727773
    },
    "6389": {
        "freezeLoc": 25,
        "freezeDur": 103
    },
    "6396": {
        "noiseLoc": 87,
        "noiseDur": 81
    },
    "6434": {
        "freezeLoc": 139,
        "freezeDur": 87
    },
    "6465": {
        "offsetLoc": 137,
        "offsetDur": 141
    },
    "6471": {
        "offsetLoc": 150,
        "offsetDur": 56
    },
    "6477": {
        "noiseLoc": 11,
        "noiseDur": 43
    },
    "6499": {
        "freezeLoc": 74,
        "freezeDur": 152
    },
    "6505": {
        "impLoc": 312,
        "impFac": 1.5946253657683158
    },
    "6519": {
        "driftLoc": 21,
        "driftDur": 221,
        "driftFact": 111.59474695214153
    },
    "6561": {
        "impLoc": 137,
        "impFac": 1.5899763426958984
    },
    "6576": {
        "driftLoc": 99,
        "driftDur": 209,
        "driftFact": 165.7752983607242
    },
    "6592": {
        "offsetLoc": 67,
        "offsetDur": 90
    },
    "6628": {
        "driftLoc": 92,
        "driftDur": 180,
        "driftFact": 289.1157574114518
    },
    "6644": {
        "offsetLoc": 178,
        "offsetDur": 80
    },
    "6655": {
        "offsetLoc": 97,
        "offsetDur": 84
    },
    "6660": {
        "noiseLoc": 144,
        "noiseDur": 132
    },
    "6682": {
        "noiseLoc": 129,
        "noiseDur": 133
    },
    "6777": {
        "noiseLoc": 21,
        "noiseDur": 70
    },
    "6779": {
        "impLoc": 136,
        "impFac": 1.8782960812205394
    },
    "6788": {
        "freezeLoc": 140,
        "freezeDur": 49
    },
    "6796": {
        "driftLoc": 41,
        "driftDur": 246,
        "driftFact": 454.22290098896116
    },
    "6813": {
        "impLoc": 36,
        "impFac": 1.4417064420145835
    },
    "6815": {
        "impLoc": 220,
        "impFac": 1.9972527163751377
    },
    "6822": {
        "noiseLoc": 63,
        "noiseDur": 150
    },
    "6845": {
        "driftLoc": 80,
        "driftDur": 237,
        "driftFact": 100.80797277924822
    },
    "6863": {
        "impLoc": 73,
        "impFac": 1.4248124422332873
    },
    "6877": {
        "offsetLoc": 39,
        "offsetDur": 70
    },
    "6920": {
        "impLoc": 202,
        "impFac": 1.5168381156012034
    },
    "6980": {
        "offsetLoc": 120,
        "offsetDur": 83
    },
    "6986": {
        "noiseLoc": 108,
        "noiseDur": 92
    },
    "7045": {
        "freezeLoc": 178,
        "freezeDur": 135
    },
    "7059": {
        "impLoc": 172,
        "impFac": 1.79358142399371
    },
    "7079": {
        "freezeLoc": 44,
        "freezeDur": 34
    },
    "7098": {
        "driftLoc": 12,
        "driftDur": 153,
        "driftFact": 285.4491910487195
    },
    "7123": {
        "driftLoc": 81,
        "driftDur": 152,
        "driftFact": 146.29019241101014
    },
    "7135": {
        "impLoc": 16,
        "impFac": 1.8353646054457444
    },
    "7139": {
        "noiseLoc": 132,
        "noiseDur": 82
    },
    "7176": {
        "impLoc": 56,
        "impFac": 1.737129953583026
    },
    "7185": {
        "offsetLoc": 95,
        "offsetDur": 86
    },
    "7186": {
        "freezeLoc": 31,
        "freezeDur": 40
    },
    "7187": {
        "offsetLoc": 93,
        "offsetDur": 137
    },
    "7203": {
        "freezeLoc": 21,
        "freezeDur": 143
    },
    "7225": {
        "noiseLoc": 198,
        "noiseDur": 66
    },
    "7235": {
        "freezeLoc": 177,
        "freezeDur": 147
    },
    "7269": {
        "offsetLoc": 78,
        "offsetDur": 69
    },
    "7288": {
        "noiseLoc": 173,
        "noiseDur": 55
    },
    "7304": {
        "freezeLoc": 117,
        "freezeDur": 56
    },
    "7305": {
        "freezeLoc": 52,
        "freezeDur": 90
    },
    "7315": {
        "offsetLoc": 104,
        "offsetDur": 39
    },
    "7326": {
        "noiseLoc": 55,
        "noiseDur": 117
    },
    "7336": {
        "freezeLoc": 158,
        "freezeDur": 142
    },
    "7346": {
        "offsetLoc": 152,
        "offsetDur": 113
    },
    "7384": {
        "offsetLoc": 83,
        "offsetDur": 91
    },
    "7417": {
        "driftLoc": 41,
        "driftDur": 204,
        "driftFact": 136.04068554427573
    },
    "7418": {
        "driftLoc": 87,
        "driftDur": 154,
        "driftFact": 116.54726018913047
    },
    "7428": {
        "impLoc": 204,
        "impFac": 1.7779678170439346
    },
    "7441": {
        "freezeLoc": 119,
        "freezeDur": 47
    },
    "7448": {
        "impLoc": 108,
        "impFac": 1.8976518577846389
    },
    "7462": {
        "impLoc": 58,
        "impFac": 1.598311501638047
    },
    "7514": {
        "offsetLoc": 43,
        "offsetDur": 58
    },
    "7518": {
        "noiseLoc": 154,
        "noiseDur": 137
    },
    "7522": {
        "noiseLoc": 103,
        "noiseDur": 103
    },
    "7535": {
        "impLoc": 170,
        "impFac": 1.4744163111450708
    },
    "7536": {
        "driftLoc": 53,
        "driftDur": 224,
        "driftFact": 349.26225150811797
    },
    "7543": {
        "offsetLoc": 8,
        "offsetDur": 36
    },
    "7550": {
        "noiseLoc": 3,
        "noiseDur": 113
    },
    "7564": {
        "noiseLoc": 177,
        "noiseDur": 60
    },
    "7569": {
        "impLoc": 143,
        "impFac": 1.4530213624932582
    },
    "7612": {
        "offsetLoc": 62,
        "offsetDur": 147
    },
    "7619": {
        "noiseLoc": 144,
        "noiseDur": 101
    },
    "7653": {
        "impLoc": 38,
        "impFac": 1.8713411332007825
    },
    "7663": {
        "noiseLoc": 110,
        "noiseDur": 72
    },
    "7667": {
        "offsetLoc": 150,
        "offsetDur": 140
    },
    "7673": {
        "offsetLoc": 59,
        "offsetDur": 70
    },
    "7680": {
        "freezeLoc": 196,
        "freezeDur": 49
    },
    "7693": {
        "offsetLoc": 153,
        "offsetDur": 60
    },
    "7716": {
        "driftLoc": 37,
        "driftDur": 195,
        "driftFact": 114.54740611311136
    },
    "7739": {
        "noiseLoc": 20,
        "noiseDur": 159
    },
    "7798": {
        "noiseLoc": 129,
        "noiseDur": 94
    },
    "7814": {
        "freezeLoc": 67,
        "freezeDur": 90
    },
    "7843": {
        "freezeLoc": 179,
        "freezeDur": 108
    },
    "7849": {
        "freezeLoc": 178,
        "freezeDur": 110
    },
    "7870": {
        "driftLoc": 29,
        "driftDur": 212,
        "driftFact": 223.2748280412637
    },
    "7872": {
        "offsetLoc": 127,
        "offsetDur": 151
    },
    "7888": {
        "freezeLoc": 21,
        "freezeDur": 115
    },
    "7897": {
        "noiseLoc": 7,
        "noiseDur": 44
    },
    "7906": {
        "freezeLoc": 198,
        "freezeDur": 88
    },
    "7924": {
        "impLoc": 281,
        "impFac": 1.5648651766735526
    },
    "7946": {
        "offsetLoc": 142,
        "offsetDur": 127
    },
    "7974": {
        "impLoc": 150,
        "impFac": 1.880677406077477
    },
    "8014": {
        "impLoc": 89,
        "impFac": 1.5518144737948192
    },
    "8038": {
        "noiseLoc": 39,
        "noiseDur": 85
    },
    "8046": {
        "driftLoc": 59,
        "driftDur": 224,
        "driftFact": 120.1277964263065
    },
    "8113": {
        "driftLoc": 89,
        "driftDur": 174,
        "driftFact": 174.0355991367212
    },
    "8126": {
        "driftLoc": 95,
        "driftDur": 197,
        "driftFact": 291.96008667160197
    },
    "8162": {
        "freezeLoc": 76,
        "freezeDur": 59
    },
    "8163": {
        "impLoc": 52,
        "impFac": 1.7789421452606389
    },
    "8188": {
        "impLoc": 237,
        "impFac": 1.6335107469823438
    },
    "8208": {
        "offsetLoc": 84,
        "offsetDur": 154
    },
    "8219": {
        "impLoc": 181,
        "impFac": 1.8426719646385652
    },
    "8224": {
        "freezeLoc": 74,
        "freezeDur": 150
    },
    "8247": {
        "offsetLoc": 4,
        "offsetDur": 106
    },
    "8252": {
        "offsetLoc": 114,
        "offsetDur": 46
    },
    "8292": {
        "driftLoc": 44,
        "driftDur": 211,
        "driftFact": 169.45176916733917
    },
    "8310": {
        "freezeLoc": 101,
        "freezeDur": 135
    },
    "8321": {
        "driftLoc": 62,
        "driftDur": 230,
        "driftFact": 188.30773437168665
    },
    "8331": {
        "noiseLoc": 124,
        "noiseDur": 152
    },
    "8390": {
        "driftLoc": 52,
        "driftDur": 243,
        "driftFact": 158.60866387068842
    },
    "8540": {
        "impLoc": 27,
        "impFac": 1.4368691661314288
    },
    "8543": {
        "impLoc": 225,
        "impFac": 1.9870719363351643
    },
    "8554": {
        "noiseLoc": 25,
        "noiseDur": 146
    },
    "8555": {
        "freezeLoc": 87,
        "freezeDur": 131
    },
    "8571": {
        "offsetLoc": 139,
        "offsetDur": 90
    },
    "8580": {
        "noiseLoc": 40,
        "noiseDur": 30
    },
    "8603": {
        "driftLoc": 64,
        "driftDur": 241,
        "driftFact": 389.6466613843836
    },
    "8627": {
        "offsetLoc": 130,
        "offsetDur": 50
    },
    "8684": {
        "noiseLoc": 177,
        "noiseDur": 153
    },
    "8704": {
        "noiseLoc": 179,
        "noiseDur": 130
    },
    "8721": {
        "freezeLoc": 104,
        "freezeDur": 48
    },
    "8799": {
        "noiseLoc": 120,
        "noiseDur": 149
    },
    "8820": {
        "noiseLoc": 146,
        "noiseDur": 74
    },
    "8846": {
        "driftLoc": 22,
        "driftDur": 169,
        "driftFact": 277.1022672685127
    },
    "8866": {
        "driftLoc": 48,
        "driftDur": 201,
        "driftFact": 460.35062601934044
    },
    "8916": {
        "freezeLoc": 32,
        "freezeDur": 88
    },
    "8934": {
        "noiseLoc": 71,
        "noiseDur": 133
    },
    "8935": {
        "freezeLoc": 22,
        "freezeDur": 118
    },
    "8975": {
        "noiseLoc": 171,
        "noiseDur": 88
    },
    "8979": {
        "impLoc": 95,
        "impFac": 1.5273636209159134
    },
    "8980": {
        "freezeLoc": 156,
        "freezeDur": 41
    },
    "8994": {
        "noiseLoc": 38,
        "noiseDur": 40
    },
    "8995": {
        "impLoc": 277,
        "impFac": 1.849687586167417
    },
    "9020": {
        "noiseLoc": 75,
        "noiseDur": 117
    },
    "9040": {
        "impLoc": 160,
        "impFac": 1.685896339002381
    },
    "9055": {
        "impLoc": 294,
        "impFac": 1.4038655458254423
    },
    "9083": {
        "offsetLoc": 147,
        "offsetDur": 44
    },
    "9087": {
        "noiseLoc": 104,
        "noiseDur": 143
    },
    "9121": {
        "driftLoc": 69,
        "driftDur": 211,
        "driftFact": 120.88819941531162
    },
    "9129": {
        "impLoc": 17,
        "impFac": 1.7378145520377584
    },
    "9136": {
        "freezeLoc": 175,
        "freezeDur": 134
    },
    "9152": {
        "impLoc": 31,
        "impFac": 1.6238268293793625
    },
    "9170": {
        "driftLoc": 14,
        "driftDur": 221,
        "driftFact": 249.48398384395784
    },
    "9210": {
        "offsetLoc": 29,
        "offsetDur": 47
    },
    "9228": {
        "freezeLoc": 24,
        "freezeDur": 125
    },
    "9235": {
        "freezeLoc": 66,
        "freezeDur": 102
    },
    "9243": {
        "noiseLoc": 83,
        "noiseDur": 70
    },
    "9289": {
        "freezeLoc": 167,
        "freezeDur": 113
    },
    "9290": {
        "offsetLoc": 124,
        "offsetDur": 151
    },
    "9323": {
        "offsetLoc": 86,
        "offsetDur": 77
    },
    "9348": {
        "freezeLoc": 101,
        "freezeDur": 108
    },
    "9379": {
        "offsetLoc": 156,
        "offsetDur": 154
    },
    "9383": {
        "driftLoc": 33,
        "driftDur": 226,
        "driftFact": 137.60684444912457
    },
    "9384": {
        "noiseLoc": 162,
        "noiseDur": 68
    },
    "9385": {
        "noiseLoc": 126,
        "noiseDur": 80
    },
    "9393": {
        "impLoc": 284,
        "impFac": 1.6224149933410899
    },
    "9432": {
        "noiseLoc": 142,
        "noiseDur": 124
    },
    "9478": {
        "driftLoc": 42,
        "driftDur": 176,
        "driftFact": 349.752517087274
    },
    "9509": {
        "driftLoc": 35,
        "driftDur": 258,
        "driftFact": 339.02212414253927
    },
    "9510": {
        "offsetLoc": 11,
        "offsetDur": 152
    },
    "9578": {
        "offsetLoc": 194,
        "offsetDur": 105
    },
    "9582": {
        "driftLoc": 25,
        "driftDur": 194,
        "driftFact": 170.59173512232704
    },
    "9592": {
        "impLoc": 78,
        "impFac": 1.8411846472722508
    },
    "9615": {
        "offsetLoc": 13,
        "offsetDur": 50
    },
    "9651": {
        "impLoc": 304,
        "impFac": 1.6120935547396118
    },
    "9706": {
        "freezeLoc": 107,
        "freezeDur": 56
    },
    "9775": {
        "offsetLoc": 186,
        "offsetDur": 56
    },
    "9776": {
        "driftLoc": 11,
        "driftDur": 225,
        "driftFact": 330.3198198963825
    },
    "9800": {
        "freezeLoc": 152,
        "freezeDur": 39
    },
    "9816": {
        "noiseLoc": 83,
        "noiseDur": 59
    },
    "9823": {
        "noiseLoc": 102,
        "noiseDur": 131
    },
    "9844": {
        "offsetLoc": 31,
        "offsetDur": 50
    },
    "9867": {
        "freezeLoc": 165,
        "freezeDur": 77
    },
    "9892": {
        "freezeLoc": 35,
        "freezeDur": 76
    },
    "9894": {
        "freezeLoc": 16,
        "freezeDur": 140
    },
    "9904": {
        "impLoc": 231,
        "impFac": 1.6329113052835462
    },
    "9906": {
        "impLoc": 291,
        "impFac": 1.4373988179097916
    },
    "9923": {
        "offsetLoc": 3,
        "offsetDur": 117
    },
    "9929": {
        "driftLoc": 94,
        "driftDur": 169,
        "driftFact": 209.55505700012958
    },
    "9932": {
        "driftLoc": 74,
        "driftDur": 156,
        "driftFact": 159.35065490943697
    },
    "9934": {
        "driftLoc": 57,
        "driftDur": 237,
        "driftFact": 352.2877482798192
    },
    "9968": {
        "freezeLoc": 67,
        "freezeDur": 157
    },
    "9974": {
        "noiseLoc": 97,
        "noiseDur": 79
    },
    "9980": {
        "driftLoc": 86,
        "driftDur": 163,
        "driftFact": 133.5572182557514
    }
}